i8_compression_tools_pip_pkg/__init__.py
i8_compression_tools_pip_pkg/gz_files.py
i8_compression_tools_pip_pkg/zstd_compress_and_split.py
i8_compression_tools_pip_pkg-0.0.0.dist-info/METADATA
i8_compression_tools_pip_pkg-0.0.0.dist-info/WHEEL
i8_compression_tools_pip_pkg-0.0.0.dist-info/licenses/LICENSE
i8_compression_tools_pip_pkg-0.0.0.dist-info/RECORD
