Metadata-Version: 2.4
Name: i8_compression_tools_pip_pkg
Version: 0.0.0
Summary: compression tools
Project-URL: Homepage, https://github.com/imahdimir/i8_compression_tools_pip_pkg
Author-email: Mahdi Mir <imahdimir@gmail.com>
License: MIT License
License-File: LICENSE
Keywords: compression
Requires-Dist: zstandard==0.23.0
